{
  "colony": "Gambia",
  "year": 1936,
  "sections": [
    {
      "name": "THE GAMBIA.",
      "type": "narrative",
      "start_line": 1,
      "end_line": 2
    },
    {
      "name": "Situation and Area.",
      "type": "narrative",
      "start_line": 3,
      "end_line": 11
    },
    {
      "name": "History.",
      "type": "narrative",
      "start_line": 12,
      "end_line": 39
    },
    {
      "name": "The Provinces are as follows:\u2014North Bank Province, with the districts of Lower Niumi, Upper Niumi, Jokadu, Lower Baddibu, Central Baddibu and Upper Baddibu. MacCarthy Island Province, with the districts of Sami, Niani, Nianija, Upper Saloum, Lower Saloum, MacCarthy Island, Fulladu West, Eastern Niamina, Western Niamina and Niamina Dankunku. Upper River Province, with the districts of Fulladu East, Kantora Wuli and Sandu. South Bank Province, with the districts of Central Jarra, Eastern Jarra, Western Jarra, Eastern Kiang and Central Kiang, Kombo St. Mary, Kombo North, Kombo South, Kombo Central, Kombo East, Foni Brefet, Bintang-Karenai, Foni Kansala, Foni Bondali, Foni Jarrol and Kiang West.",
      "type": "narrative",
      "start_line": 40,
      "end_line": 40
    },
    {
      "name": "Inhabitants of the Gambia.",
      "type": "narrative",
      "start_line": 42,
      "end_line": 53
    },
    {
      "name": "Industry, Trade and Customs.",
      "type": "narrative",
      "start_line": 54,
      "end_line": 67
    },
    {
      "name": "The principal imports are cotton goods, rice, kola nuts.",
      "type": "narrative",
      "start_line": 68,
      "end_line": 68
    },
    {
      "name": "The principal exports in 1934 were:",
      "type": "statistics",
      "start_line": 69,
      "end_line": 77
    },
    {
      "name": "The following table shows the percentages of imports and exports by countries:",
      "type": "statistics",
      "start_line": 78,
      "end_line": 88
    },
    {
      "name": "A new Customs Tariff Ordinance was passed in 1932, giving preferential treatment to British manufactures and products. The *ad valorem* rates of duties are 10% on British goods and 12\u00bd% on foreign goods, except in the case of carriages and parts thereof (inclusive of motor cars and tyres) where the duties are 5% *ad valorem* on British goods and 25% *ad valorem* on foreign goods. In the case of goods subject to specific duties, a similar preference is given to British goods.",
      "type": "narrative",
      "start_line": 89,
      "end_line": 97
    },
    {
      "name": "**Relations with the Interior.**",
      "type": "narrative",
      "start_line": 99,
      "end_line": 104
    },
    {
      "name": "**Currency and Banking.**",
      "type": "narrative",
      "start_line": 105,
      "end_line": 110
    },
    {
      "name": "**Land.**",
      "type": "narrative",
      "start_line": 111,
      "end_line": 114
    },
    {
      "name": "**Education.**",
      "type": "narrative",
      "start_line": 115,
      "end_line": 120
    },
    {
      "name": "**Means of Communication.**",
      "type": "narrative",
      "start_line": 121,
      "end_line": 134
    },
    {
      "name": "The following are the rates of postage:",
      "type": "narrative",
      "start_line": 135,
      "end_line": 169
    },
    {
      "name": "**Climate.**",
      "type": "narrative",
      "start_line": 170,
      "end_line": 175
    },
    {
      "name": "**FINANCES.**",
      "type": "statistics",
      "start_line": 176,
      "end_line": 190
    },
    {
      "name": "**IMPORTS.**",
      "type": "statistics",
      "start_line": 191,
      "end_line": 207
    },
    {
      "name": "**EXPORTS.**",
      "type": "statistics",
      "start_line": 208,
      "end_line": 228
    },
    {
      "name": "**Governors.**",
      "type": "narrative",
      "start_line": 229,
      "end_line": 239
    },
    {
      "name": "**Executive Council.**",
      "type": "council",
      "start_line": 240,
      "end_line": 249
    },
    {
      "name": "**Legislative Council.**",
      "type": "council",
      "start_line": 250,
      "end_line": 273
    },
    {
      "name": "CIVIL ESTABLISHMENT.",
      "type": "personnel",
      "start_line": 274,
      "end_line": 279
    },
    {
      "name": "Secretariat.",
      "type": "personnel",
      "start_line": 280,
      "end_line": 290
    },
    {
      "name": "Printing Branch.",
      "type": "personnel",
      "start_line": 291,
      "end_line": 294
    },
    {
      "name": "Receiver-General's Department.",
      "type": "personnel",
      "start_line": 295,
      "end_line": 310
    },
    {
      "name": "Posts and Telegraph Branch.",
      "type": "personnel",
      "start_line": 311,
      "end_line": 316
    },
    {
      "name": "Legal Department.",
      "type": "personnel",
      "start_line": 317,
      "end_line": 328
    },
    {
      "name": "Education.",
      "type": "personnel",
      "start_line": 329,
      "end_line": 332
    },
    {
      "name": "Provincial Administration.",
      "type": "personnel",
      "start_line": 333,
      "end_line": 336
    },
    {
      "name": "Police Force.",
      "type": "personnel",
      "start_line": 337,
      "end_line": 346
    },
    {
      "name": "Prison.",
      "type": "personnel",
      "start_line": 347,
      "end_line": 350
    },
    {
      "name": "Medical.",
      "type": "personnel",
      "start_line": 351,
      "end_line": 362
    },
    {
      "name": "Health Department.",
      "type": "personnel",
      "start_line": 363,
      "end_line": 370
    },
    {
      "name": "Public Works Department.",
      "type": "personnel",
      "start_line": 371,
      "end_line": 390
    },
    {
      "name": "Land and Survey Department.",
      "type": "personnel",
      "start_line": 391,
      "end_line": 398
    },
    {
      "name": "Audit Office.",
      "type": "personnel",
      "start_line": 399,
      "end_line": 404
    },
    {
      "name": "Marine.",
      "type": "personnel",
      "start_line": 405,
      "end_line": 414
    },
    {
      "name": "Agricultural Department.",
      "type": "personnel",
      "start_line": 415,
      "end_line": 420
    },
    {
      "name": "Royal West African Frontier Force.",
      "type": "personnel",
      "start_line": 421,
      "end_line": 427
    },
    {
      "name": "Foreign Consuls.",
      "type": "narrative",
      "start_line": 428,
      "end_line": 445
    }
  ]
}