{
  "colony": "Sierra Leone",
  "year": 1956,
  "sections": [
    {
      "name": "SIERRA LEONE",
      "type": "narrative",
      "start_line": 1,
      "end_line": 40
    },
    {
      "name": "History",
      "type": "narrative",
      "start_line": 41,
      "end_line": 55
    },
    {
      "name": "**Land Policy**",
      "type": "narrative",
      "start_line": 56,
      "end_line": 59
    },
    {
      "name": "**Taxation**",
      "type": "narrative",
      "start_line": 60,
      "end_line": 65
    },
    {
      "name": "**Public Finance**",
      "type": "statistics",
      "start_line": 66,
      "end_line": 91
    },
    {
      "name": "**Currency**",
      "type": "narrative",
      "start_line": 92,
      "end_line": 95
    },
    {
      "name": "**Development Plans**",
      "type": "narrative",
      "start_line": 96,
      "end_line": 121
    },
    {
      "name": "**Education**",
      "type": "narrative",
      "start_line": 122,
      "end_line": 142
    },
    {
      "name": "Health",
      "type": "narrative",
      "start_line": 143,
      "end_line": 147
    },
    {
      "name": "Communications",
      "type": "narrative",
      "start_line": 148,
      "end_line": 162
    },
    {
      "name": "Broadcasting",
      "type": "narrative",
      "start_line": 163,
      "end_line": 167
    },
    {
      "name": "Principal Occupations",
      "type": "narrative",
      "start_line": 168,
      "end_line": 175
    },
    {
      "name": "Main Crops and Products",
      "type": "narrative",
      "start_line": 176,
      "end_line": 201
    },
    {
      "name": "Trade",
      "type": "statistics",
      "start_line": 202,
      "end_line": 245
    },
    {
      "name": "Marketing and Co-operative Organizations",
      "type": "narrative",
      "start_line": 246,
      "end_line": 252
    },
    {
      "name": "EXECUTIVE COUNCIL",
      "type": "council",
      "start_line": 253,
      "end_line": 273
    },
    {
      "name": "LEGISLATIVE COUNCIL",
      "type": "council",
      "start_line": 274,
      "end_line": 296
    },
    {
      "name": "CIVIL ESTABLISHMENT",
      "type": "personnel",
      "start_line": 297,
      "end_line": 351
    }
  ]
}