{
  "colony": "Sierra Leone",
  "year": 1951,
  "sections": [
    {
      "name": "SIERRA LEONE",
      "type": "narrative",
      "start_line": 1,
      "end_line": 2
    },
    {
      "name": "Situation and Area",
      "type": "narrative",
      "start_line": 3,
      "end_line": 8
    },
    {
      "name": "Climate",
      "type": "narrative",
      "start_line": 9,
      "end_line": 14
    },
    {
      "name": "General Description",
      "type": "narrative",
      "start_line": 15,
      "end_line": 35
    },
    {
      "name": "POPULATION",
      "type": "statistics",
      "start_line": 36,
      "end_line": 51
    },
    {
      "name": "RELIGION",
      "type": "narrative",
      "start_line": 52,
      "end_line": 57
    },
    {
      "name": "HISTORY",
      "type": "narrative",
      "start_line": 58,
      "end_line": 65
    },
    {
      "name": "CONSTITUTION",
      "type": "narrative",
      "start_line": 66,
      "end_line": 80
    },
    {
      "name": "ADMINISTRATION",
      "type": "narrative",
      "start_line": 81,
      "end_line": 102
    },
    {
      "name": "SOCIAL SERVICES",
      "type": "narrative",
      "start_line": 103,
      "end_line": 159
    },
    {
      "name": "Communications",
      "type": "narrative",
      "start_line": 160,
      "end_line": 174
    },
    {
      "name": "Shipping",
      "type": "narrative",
      "start_line": 175,
      "end_line": 192
    },
    {
      "name": "Public Finance",
      "type": "statistics",
      "start_line": 193,
      "end_line": 218
    },
    {
      "name": "Air",
      "type": "narrative",
      "start_line": 222,
      "end_line": 225
    },
    {
      "name": "Posts and Telegraphs",
      "type": "narrative",
      "start_line": 226,
      "end_line": 232
    },
    {
      "name": "Currency and Banking",
      "type": "narrative",
      "start_line": 233,
      "end_line": 237
    },
    {
      "name": "PRODUCTION AND TRADE",
      "type": "narrative",
      "start_line": 238,
      "end_line": 251
    },
    {
      "name": "IMPORTS",
      "type": "statistics",
      "start_line": 252,
      "end_line": 267
    },
    {
      "name": "EXPORTS",
      "type": "statistics",
      "start_line": 268,
      "end_line": 281
    },
    {
      "name": "GOVERNORS",
      "type": "narrative",
      "start_line": 282,
      "end_line": 313
    },
    {
      "name": "EXECUTIVE COUNCIL",
      "type": "council",
      "start_line": 314,
      "end_line": 332
    },
    {
      "name": "LEGISLATIVE COUNCIL",
      "type": "council",
      "start_line": 333,
      "end_line": 358
    },
    {
      "name": "FOREIGN CONSULAR OFFICERS",
      "type": "narrative",
      "start_line": 359,
      "end_line": 368
    },
    {
      "name": "SHORT SELECT BIBLIOGRAPHY",
      "type": "narrative",
      "start_line": 369,
      "end_line": 376
    },
    {
      "name": "CIVIL ESTABLISHMENT",
      "type": "personnel",
      "start_line": 377,
      "end_line": 431
    },
    {
      "name": "ADMINISTRATION",
      "type": "personnel",
      "start_line": 432,
      "end_line": 459
    },
    {
      "name": "ACCOUNTANT-GENERAL",
      "type": "personnel",
      "start_line": 459,
      "end_line": 465
    },
    {
      "name": "AGRICULTURE",
      "type": "personnel",
      "start_line": 465,
      "end_line": 483
    },
    {
      "name": "AUDIT",
      "type": "personnel",
      "start_line": 483,
      "end_line": 491
    },
    {
      "name": "CIVIL AVIATION",
      "type": "personnel",
      "start_line": 491,
      "end_line": 497
    },
    {
      "name": "COMMERCE AND INDUSTRY",
      "type": "personnel",
      "start_line": 497,
      "end_line": 515
    },
    {
      "name": "CO-OPERATIVE SOCIETIES",
      "type": "personnel",
      "start_line": 515,
      "end_line": 519
    },
    {
      "name": "CUSTOMS",
      "type": "personnel",
      "start_line": 519,
      "end_line": 527
    },
    {
      "name": "EDUCATION",
      "type": "personnel",
      "start_line": 527,
      "end_line": 541
    },
    {
      "name": "FORESTRY",
      "type": "personnel",
      "start_line": 541,
      "end_line": 550
    },
    {
      "name": "Geological Survey",
      "type": "personnel",
      "start_line": 550,
      "end_line": 556
    },
    {
      "name": "Income Tax",
      "type": "personnel",
      "start_line": 556,
      "end_line": 566
    },
    {
      "name": "Judicial",
      "type": "personnel",
      "start_line": 566,
      "end_line": 576
    },
    {
      "name": "Labour",
      "type": "personnel",
      "start_line": 576,
      "end_line": 582
    },
    {
      "name": "Legal",
      "type": "personnel",
      "start_line": 582,
      "end_line": 592
    },
    {
      "name": "Medical",
      "type": "personnel",
      "start_line": 592,
      "end_line": 618
    },
    {
      "name": "Health",
      "type": "personnel",
      "start_line": 618,
      "end_line": 624
    },
    {
      "name": "Meteorological",
      "type": "personnel",
      "start_line": 624,
      "end_line": 630
    },
    {
      "name": "Mines",
      "type": "personnel",
      "start_line": 630,
      "end_line": 636
    },
    {
      "name": "Police",
      "type": "personnel",
      "start_line": 636,
      "end_line": 648
    },
    {
      "name": "Port and Marine",
      "type": "personnel",
      "start_line": 648,
      "end_line": 652
    },
    {
      "name": "Post Office",
      "type": "personnel",
      "start_line": 652,
      "end_line": 666
    },
    {
      "name": "Engineering",
      "type": "personnel",
      "start_line": 666,
      "end_line": 672
    },
    {
      "name": "Printing",
      "type": "personnel",
      "start_line": 672,
      "end_line": 676
    },
    {
      "name": "Prisons",
      "type": "personnel",
      "start_line": 676,
      "end_line": 684
    },
    {
      "name": "Public Works",
      "type": "personnel",
      "start_line": 684,
      "end_line": 714
    },
    {
      "name": "Electricity",
      "type": "personnel",
      "start_line": 714,
      "end_line": 723
    },
    {
      "name": "Land Drainage",
      "type": "personnel",
      "start_line": 723,
      "end_line": 727
    },
    {
      "name": "Public Relations",
      "type": "personnel",
      "start_line": 727,
      "end_line": 731
    },
    {
      "name": "Railway Management",
      "type": "personnel",
      "start_line": 731,
      "end_line": 736
    },
    {
      "name": "Accounts",
      "type": "personnel",
      "start_line": 736,
      "end_line": 741
    },
    {
      "name": "Stores",
      "type": "personnel",
      "start_line": 741,
      "end_line": 746
    },
    {
      "name": "Engineering",
      "type": "personnel",
      "start_line": 746,
      "end_line": 750
    },
    {
      "name": "Locomotive",
      "type": "personnel",
      "start_line": 750,
      "end_line": 757
    },
    {
      "name": "Traffic",
      "type": "personnel",
      "start_line": 757,
      "end_line": 764
    },
    {
      "name": "Road Transport",
      "type": "personnel",
      "start_line": 764,
      "end_line": 769
    },
    {
      "name": "Surveys and Lands",
      "type": "personnel",
      "start_line": 769,
      "end_line": 776
    },
    {
      "name": "Veterinary",
      "type": "personnel",
      "start_line": 776,
      "end_line": 782
    }
  ]
}